brutils_py/__init__.py
brutils_py/cep.py
brutils_py/cnh.py
brutils_py/cnpj.py
brutils_py/cpf.py
brutils_py/nis.py
brutils_py/phone.py
brutils_py/pis.py
brutils_py/rg.py
brutils_py/te.py
brutils_py/utils.py
brutils_py/vehicle_plate.py
brutils_py-0.1.0.dist-info/licenses/LICENSE
tests/__init__.py
tests/test_cep.py
tests/test_cnh.py
tests/test_cnpj.py
tests/test_cpf.py
tests/test_nis.py
tests/test_pis.py
tests/test_rg.py
tests/test_te.py
tests/test_vehicle_plate.py
tests/tests_phone.py
brutils_py-0.1.0.dist-info/METADATA
brutils_py-0.1.0.dist-info/WHEEL
brutils_py-0.1.0.dist-info/top_level.txt
brutils_py-0.1.0.dist-info/RECORD
