Metadata-Version: 2.4
Name: brutils_py
Version: 0.1.0
Summary: Library for generation, validation and formatting of Brazilian data (CPF, CNPJ, RG, CEP, CNH, etc.)
Home-page: https://github.com/JGuylherme/brutils_py
Author: Guy
License: MIT
Classifier: Programming Language :: Python :: 3
Classifier: License :: OSI Approved :: MIT License
Classifier: Operating System :: OS Independent
Classifier: Development Status :: 4 - Beta
Classifier: Intended Audience :: Developers
Classifier: Topic :: Software Development :: Libraries :: Python Modules
Requires-Python: >=3.12
License-File: LICENSE
Requires-Dist: requests
Provides-Extra: dev
Requires-Dist: pytest; extra == "dev"
Requires-Dist: pytest-mock; extra == "dev"
Requires-Dist: Faker; extra == "dev"
Dynamic: license-file
